a2ml/__init__.py
a2ml/api/__init__.py
a2ml/api/a2ml.py
a2ml/api/a2ml_credentials.py
a2ml/api/a2ml_dataset.py
a2ml/api/a2ml_experiment.py
a2ml/api/a2ml_model.py
a2ml/api/a2ml_project.py
a2ml/api/base_a2ml.py
a2ml/api/auger/__init__.py
a2ml/api/auger/a2ml.py
a2ml/api/auger/config.py
a2ml/api/auger/credentials.py
a2ml/api/auger/dataset.py
a2ml/api/auger/experiment.py
a2ml/api/auger/model.py
a2ml/api/auger/project.py
a2ml/api/auger/impl/__init__.py
a2ml/api/auger/impl/dataset.py
a2ml/api/auger/impl/decorators.py
a2ml/api/auger/impl/exceptions.py
a2ml/api/auger/impl/experiment.py
a2ml/api/auger/impl/model.py
a2ml/api/auger/impl/project.py
a2ml/api/auger/impl/cloud/__init__.py
a2ml/api/auger/impl/cloud/actual.py
a2ml/api/auger/impl/cloud/auth.py
a2ml/api/auger/impl/cloud/base.py
a2ml/api/auger/impl/cloud/cluster.py
a2ml/api/auger/impl/cloud/cluster_task.py
a2ml/api/auger/impl/cloud/dataset.py
a2ml/api/auger/impl/cloud/endpoint.py
a2ml/api/auger/impl/cloud/endpoint_pipeline.py
a2ml/api/auger/impl/cloud/experiment.py
a2ml/api/auger/impl/cloud/experiment_session.py
a2ml/api/auger/impl/cloud/org.py
a2ml/api/auger/impl/cloud/pipeline.py
a2ml/api/auger/impl/cloud/pipeline_file.py
a2ml/api/auger/impl/cloud/prediction.py
a2ml/api/auger/impl/cloud/project.py
a2ml/api/auger/impl/cloud/project_file.py
a2ml/api/auger/impl/cloud/rest_api.py
a2ml/api/auger/impl/cloud/review_alert.py
a2ml/api/auger/impl/cloud/review_alert_item.py
a2ml/api/auger/impl/cloud/trial.py
a2ml/api/auger/impl/mparts/__init__.py
a2ml/api/auger/impl/mparts/actual.py
a2ml/api/auger/impl/mparts/delete_actual.py
a2ml/api/auger/impl/mparts/deploy.py
a2ml/api/auger/impl/mparts/predict.py
a2ml/api/auger/impl/mparts/undeploy.py
a2ml/api/azure/__init__.py
a2ml/api/azure/a2ml.py
a2ml/api/azure/credentials.py
a2ml/api/azure/dataset.py
a2ml/api/azure/exceptions.py
a2ml/api/azure/experiment.py
a2ml/api/azure/model.py
a2ml/api/azure/project.py
a2ml/api/google/__init__.py
a2ml/api/google/a2ml.py
a2ml-1.1.0.dist-info/LICENSE
a2ml-1.1.0.dist-info/METADATA
a2ml-1.1.0.dist-info/WHEEL
a2ml-1.1.0.dist-info/entry_points.txt
a2ml-1.1.0.dist-info/top_level.txt
a2ml-1.1.0.dist-info/RECORD
