Metadata-Version: 2.1
Name: a2ml
Version: 1.1.0
Summary: A powerful API to Automate Machine Learning workflows from multiple vendors.
Home-page: https://a2ml.org
Author: Auger AI
Author-email: hello@auger.ai
License: Apache License 2.0
Project-URL: Documentation, https://a2ml.org
Project-URL: Changelog, https://github.com/augerai/a2ml/releases
Project-URL: Issue Tracker, https://github.com/augerai/a2ml/issues
Keywords: azure,augerai,ai,machine learning,automl,deeplearn,api,sdk
Platform: any
Classifier: Development Status :: 5 - Production/Stable
Classifier: Intended Audience :: Developers
Classifier: Intended Audience :: System Administrators
Classifier: Topic :: Software Development :: Build Tools
Classifier: License :: OSI Approved :: Apache Software License
Classifier: Programming Language :: Python :: 3
Classifier: Programming Language :: Python :: 3.8
Classifier: Programming Language :: Python :: 3.11
Classifier: Programming Language :: Python :: 3 :: Only
License-File: LICENSE
Requires-Dist: numpy==1.23.5
Requires-Dist: pandas==1.5.0
Requires-Dist: joblib
Requires-Dist: ruamel.yaml
Requires-Dist: pyarrow
Requires-Dist: scipy==1.9.3
Requires-Dist: asyncio
Requires-Dist: boto3
Requires-Dist: auger-hub-api-client==0.7.4
Requires-Dist: click
Requires-Dist: shortuuid
Requires-Dist: docutils<0.16,>=0.10
Requires-Dist: requests
Requires-Dist: smart-open==6.2.0
Requires-Dist: jsonpickle
Requires-Dist: websockets
Requires-Dist: liac-arff==2.4.0
Requires-Dist: xlrd==2.0.1
Requires-Dist: multiprocess
Provides-Extra: all
Requires-Dist: flake8<=3.7.9,>=3.1.0; extra == "all"
Requires-Dist: mock; extra == "all"
Requires-Dist: pytest; extra == "all"
Requires-Dist: pytest-cov; extra == "all"
Requires-Dist: pytest-runner; extra == "all"
Requires-Dist: pytest-xdist; extra == "all"
Requires-Dist: twine; extra == "all"
Requires-Dist: vcrpy; extra == "all"
Requires-Dist: wheel<0.31.0,>=0.30.0; extra == "all"
Requires-Dist: sphinx; extra == "all"
Requires-Dist: anyio==3.7.1; extra == "all"
Requires-Dist: celery==5.2.7; extra == "all"
Requires-Dist: fastapi==0.85; extra == "all"
Requires-Dist: gevent; extra == "all"
Requires-Dist: redis; extra == "all"
Requires-Dist: s3fs<0.5.0,>=0.4.0; extra == "all"
Requires-Dist: uvicorn; extra == "all"
Requires-Dist: scikit-learn==1.2.0; extra == "all"
Provides-Extra: azure
Requires-Dist: azureml-sdk[automl]==1.29.0; extra == "azure"
Provides-Extra: docs
Requires-Dist: sphinx; extra == "docs"
Provides-Extra: google
Requires-Dist: google-cloud-automl; extra == "google"
Provides-Extra: predict
Requires-Dist: auger.ai.predict[all]==1.1.012; extra == "predict"
Provides-Extra: predict_no_cat_lgbm
Requires-Dist: auger.ai.predict[no_cat_lgbm]==1.1.012; extra == "predict-no-cat-lgbm"
Provides-Extra: predict_no_lgbm
Requires-Dist: auger.ai.predict[no_cat_lgbm]==1.1.012; extra == "predict-no-lgbm"
Requires-Dist: catboost; extra == "predict-no-lgbm"
Provides-Extra: server
Requires-Dist: anyio==3.7.1; extra == "server"
Requires-Dist: celery==5.2.7; extra == "server"
Requires-Dist: fastapi==0.85; extra == "server"
Requires-Dist: gevent; extra == "server"
Requires-Dist: redis; extra == "server"
Requires-Dist: s3fs<0.5.0,>=0.4.0; extra == "server"
Requires-Dist: uvicorn; extra == "server"
Requires-Dist: scikit-learn==1.2.0; extra == "server"
Provides-Extra: testing
Requires-Dist: flake8<=3.7.9,>=3.1.0; extra == "testing"
Requires-Dist: mock; extra == "testing"
Requires-Dist: pytest; extra == "testing"
Requires-Dist: pytest-cov; extra == "testing"
Requires-Dist: pytest-runner; extra == "testing"
Requires-Dist: pytest-xdist; extra == "testing"
Requires-Dist: twine; extra == "testing"
Requires-Dist: vcrpy; extra == "testing"
Requires-Dist: wheel<0.31.0,>=0.30.0; extra == "testing"
